<Module>
  <Name value="Workshop Stash RON"/>
  <Id value="WorkshopStashRON"/>
  <Version value="v1.1.5"/>
  <SingleplayerModule value="true"/>
  <MultiplayerModule value="false"/>
  <DependedModules>
    <DependedModule Id="Native" Version="e1.5.10"/>
    <DependedModule Id="SandBoxCore" Version="e1.5.10"/>
    <DependedModule Id="Sandbox" Version="e1.5.10"/>
    <DependedModule Id="StoryMode" Version="e1.5.10"/>
  </DependedModules>
  <SubModules>
    <SubModule>
      <Name value="WorkshopStashRON"/>
      <DLLName value="WorkshopStashRON.dll"/>
      <SubModuleClassType value="WorkshopStashRON.SubModule"/>
      <Tags>
        <Tag key="DedicatedServerType" value="none" />
        <Tag key="IsNoRenderModeElement" value="false" />
      </Tags>
    </SubModule>
  </SubModules>
  <Xmls/>
</Module>